pyguymer3/__init__.py
pyguymer3/__main__.py
pyguymer3/checkSudokuBoard.py
pyguymer3/consts.py
pyguymer3/convert_bytes_to_pretty_bytes.py
pyguymer3/convert_pretty_bytes_to_bytes.py
pyguymer3/convert_seconds_to_pretty_time.py
pyguymer3/convert_spreadsheet_to_datetime.py
pyguymer3/convert_spreadsheet_to_unix.py
pyguymer3/download.py
pyguymer3/download_file.py
pyguymer3/download_header.py
pyguymer3/download_stream.py
pyguymer3/download_text.py
pyguymer3/elem2dict.py
pyguymer3/find_instances_of_a_file.py
pyguymer3/find_integer_divisors.py
pyguymer3/find_program_version.py
pyguymer3/generate_password.py
pyguymer3/generate_random_stub.py
pyguymer3/getatime.py
pyguymer3/getctime.py
pyguymer3/getmtime.py
pyguymer3/git_commits.py
pyguymer3/git_files.py
pyguymer3/git_remote.py
pyguymer3/gzip.py
pyguymer3/hostname.py
pyguymer3/interpolate.py
pyguymer3/intersection.py
pyguymer3/make_path_safe.py
pyguymer3/mean.py
pyguymer3/nlines.py
pyguymer3/now.py
pyguymer3/perms.py
pyguymer3/remove_almost_empty_directories.py
pyguymer3/return_file_list.py
pyguymer3/return_folder_list.py
pyguymer3/return_folder_size.py
pyguymer3/return_link_list.py
pyguymer3/save_file_if_needed.py
pyguymer3/serializer.py
pyguymer3/sha256.py
pyguymer3/sha256_of_GZ.py
pyguymer3/sha256_of_MP4.py
pyguymer3/sha512.py
pyguymer3/sha512_of_GZ.py
pyguymer3/sha512_of_MP4.py
pyguymer3/start_session.py
pyguymer3/stat.py
pyguymer3/stddev.py
pyguymer3/stderr.py
pyguymer3/tar.py
pyguymer3/var.py
pyguymer3/xz.py
pyguymer3/data/README.md
pyguymer3/data/geojson/README.md
pyguymer3/data/geojson/GLOBE/README.md
pyguymer3/data/geojson/GLOBE/scale=08km/elev=0250m.geojson
pyguymer3/data/geojson/GLOBE/scale=08km/elev=0500m.geojson
pyguymer3/data/geojson/GLOBE/scale=08km/elev=0750m.geojson
pyguymer3/data/geojson/GLOBE/scale=08km/elev=1000m.geojson
pyguymer3/data/geojson/GLOBE/scale=08km/elev=1250m.geojson
pyguymer3/data/geojson/GLOBE/scale=08km/elev=1500m.geojson
pyguymer3/data/geojson/GLOBE/scale=08km/elev=1750m.geojson
pyguymer3-0.0.10.dist-info/licenses/LICENCE.txt
pyguymer3-0.0.10.dist-info/METADATA
pyguymer3-0.0.10.dist-info/WHEEL
pyguymer3-0.0.10.dist-info/top_level.txt
pyguymer3-0.0.10.dist-info/RECORD
