Metadata-Version: 2.4
Name: PyGuymer3
Version: 0.0.10
Summary: A Python 3 module containing a bunch of random functions that I have written over the years
Author: Thomas Guymer
Maintainer: Thomas Guymer
License: Apache-2.0
Project-URL: Documentation, https://pyguymer3.readthedocs.io
Project-URL: Homepage, https://github.com/Guymer/PyGuymer3
Project-URL: Issues, https://github.com/Guymer/PyGuymer3/issues
Project-URL: Funding, https://github.com/sponsors/Guymer
Classifier: Development Status :: 5 - Production/Stable
Classifier: Environment :: Console
Classifier: Intended Audience :: Developers
Classifier: Intended Audience :: Information Technology
Classifier: Intended Audience :: Science/Research
Classifier: Intended Audience :: System Administrators
Classifier: License :: OSI Approved :: Apache Software License
Classifier: Natural Language :: English
Classifier: Operating System :: MacOS :: MacOS X
Classifier: Operating System :: POSIX :: BSD :: FreeBSD
Classifier: Operating System :: POSIX :: Linux
Classifier: Programming Language :: Fortran
Classifier: Programming Language :: Python :: 3
Classifier: Programming Language :: Unix Shell
Requires-Python: >=3.11
License-File: LICENCE.txt
Requires-Dist: cartopy
Requires-Dist: exifread
Requires-Dist: geojson
Requires-Dist: lxml
Requires-Dist: matplotlib
Requires-Dist: numpy
Requires-Dist: pillow
Requires-Dist: requests
Requires-Dist: scipy
Requires-Dist: shapely
Dynamic: license-file
